keeper/__init__.py
keeper/apps.py
keeper/operators.py
keeper/permissions.py
keeper/security.py
keeper/views.py
keeper/templatetags/__init__.py
keeper/templatetags/keeper.py
django_keeper-0.6.0.dist-info/LICENSE
django_keeper-0.6.0.dist-info/METADATA
django_keeper-0.6.0.dist-info/WHEEL
django_keeper-0.6.0.dist-info/top_level.txt
django_keeper-0.6.0.dist-info/RECORD
