Metadata-Version: 2.2
Name: django-keeper
Version: 0.6.0
Summary: Authorization library for Django, with ACL, not depends on models.
Home-page: https://github.com/hirokiky/django-keeper/
Author: Hiroki KIYOHARA
Author-email: hirokiky@gmail.com
License: MIT
License-File: LICENSE
Requires-Dist: Django<5.3,>=2.2
Dynamic: author
Dynamic: author-email
Dynamic: description
Dynamic: description-content-type
Dynamic: home-page
Dynamic: license
Dynamic: requires-dist
Dynamic: summary
